<?xml version="1.0" encoding="UTF-8" standalone="no"?>
<pk><wd nm="sitioned" rd="0,0:5573|31,0:21088|40,0:3627,3743|54,0:15872|57,0:13996|60,0:14461|68,0:17447|88,0:24377|89,0:23390|90,0:24307|91,0:27740|92,0:24660|93,0:23656|162,0:12834|163,0:2327|177,0:10855|187,0:37915|190,0:1760,3344,3636|215,0:18612|220,0:18769|231,0:20067|241,0:12429|247,0:11945|251,0:14742|255,0:7333|271,0:17585"/><wd nm="sitioning" rd="16,0:2836,3797|37,0:7830|190,0:3685"/><wd nm="sitioningrid" rd="177,0:20272"/><wd nm="sitions" rd="5,0:2850,3243,5010,5449,5826|16,0:2932,4623|17,0:1110,1413|18,0:7167|33,0:1672,1750,6240,6658,6705,8218,8327,9950,10001,10052,10590,17646|37,0:211|40,0:190,275,3303,3330,4151,10314,10401,10487,10583|87,0:2100|88,0:31312|89,0:29576|90,0:31332|91,0:34875|92,0:31594|93,0:29842|162,0:15503|175,0:5152,11026|187,0:10115,10193,11720,12638,13048|241,0:15098|256,0:5913"/><wd nm="sitive" rd="5,0:5949|16,0:1519|31,0:7259|33,0:10071|37,0:10330,10454|40,0:9343|46,0:2297,2417,5020,5144|57,0:4376|60,0:4895|68,0:5799|71,0:835|88,0:10180,28383,32956|89,0:10037,26647,31220|90,0:10633,28314,32976|91,0:10782,10999,31746,36519|92,0:28665,33238|93,0:26913,31486|94,0:1667,1710|95,0:1419|156,0:604|162,0:17391|198,0:2779|215,0:6406|220,0:6594|231,0:7285|241,0:16986|247,0:2816|251,0:4230|256,0:7536|271,0:5903"/><wd nm="sitor" rd="158,0:672"/><wd nm="sits" rd="0,0:979,1663|157,0:1275,1760|158,0:437,679,958,1255|160,0:2045,2933,2968|162,0:576,882"/><wd nm="situation" rd="1,0:2113|33,0:13604|74,0:1750|88,0:37834,37900|89,0:36407,36473|90,0:37857,37923|91,0:41399,41465|92,0:38119,38185|93,0:36673,36739|94,0:5521,6404|242,0:2362"/><wd nm="sive" rd="8,128:17,41,65,1839,2222,3960|14,0:1022,1275|31,0:17650|54,0:12428|56,0:1726|57,0:8844|60,0:9314|68,0:14003|69,0:1705,1958|88,0:4298,4429,16911,26655|89,0:3898,16926,25668|90,0:4240,4371,17364,26585|91,0:4219,4350,18477,22047,30018|92,0:4450,4581,17188,26937|93,0:3940,17185,25934|115,0:10540|119,0:7067|148,0:5414,5671,6951|162,0:8115|172,0:1165|185,0:1179,1968,2600|189,0:210|215,0:15174|220,0:15331|231,0:16629|241,0:8018|247,0:7787|251,0:8948|271,0:14150"/><wd nm="sively" rd="8,0:2269,2596,3135|31,0:17463,17516|54,0:12241,12294|57,0:8657,8710|60,0:9127,9180|68,0:13816,13869|86,0:2037|88,0:16724,16777|89,0:16739,16792|90,0:17177,17230|91,0:18290,18343,21858,21912|92,0:17001,17054|93,0:16998,17051|105,0:257,1133|109,0:81,1100|117,0:8951|150,0:239,1232|162,0:7928,7981|184,0:592|187,0:21772,22200|202,0:254,1016|215,0:14987,15040|220,0:15144,15197|231,0:16442,16495|241,0:7831,7884|244,0:1952|247,0:7600,7653|251,0:8761,8814|252,0:403|271,0:13963,14016"/><wd nm="six" rd="187,0:37543|261,0:3225,3318"/><wd nm="sixth" rd="146,0:9151"/><wd nm="sizable" rd="17,0:3850|33,0:516,1523,11759,11955,12738,17282|107,0:1749|108,0:251,712,1147,2569,2701,2833,2965,3097,3229,3484,3615,3746,3877,4008,4139|141,0:3563,4395,4440|144,0:1701,2492|164,0:6634|187,0:572,616,7379,8304,8701,9348,9475,9600,9667,12274,41113"/><wd nm="size" rd="0,0:666,725,1331,1393,3753,3814,3910,3958|7,0:4617|16,0:4509,4608|17,0:92,129,274,331,393,419,1103,1425,2291,5155,6267,6307|19,0:3075|31,0:4290,4331,4404,4498,4646,5201,22046,22965,23013,23109|33,0:127,187,796,853,915,941,1021,1374,2083,11022,12329,12939,13052,13977,14031,14143,14220,14338,15528,17152|34,0:5531,6316|37,0:1309,2627,2690,2901,4147,4210,8787,10051,11108|39,0:3343,3483,3600,4217,4338,4437|40,0:616,1357,2421,3962,4118|44,0:690,714,752,795,3131,3171,4107,4954,5079,5184,5250,5986,6093,6181|45,0:1438,2833|46,0:302,1948,3860,4723,9357,9397|54,0:2954,2995,3068,3162,3357,3916,16831,17736,17784,17880|57,0:3812,3906,15115,15163,15259|60,0:4331,4425,15420,16329,16377,16473|61,0:995|68,0:2991,3032,3105,3199,3347,3910,18407,19316,19364,19460|72,0:1632,2076|75,0:1130,1997|80,0:2670|82,0:902,1389|87,0:1153,1684|88,0:1326,2188,9001,9095,21927,25336,29591,29639,29735,30120,30174,30275,30582,30682,32905,37045,37079,41098|89,0:8858,8952,24349,27856,27904,28000,28385,28439,28540,28847,28947,31169,35618,35652|90,0:1326,2163,9454,9548,21961,25266,29612,29660,29756,30141,30195,30296,30603,30703,32925,37068,37102,41517|91,0:1434,2266,9433,9527,25290,28699,33154,33202,33298,33683,33737,33838,34145,34245,36468,40611,40645,45232|92,0:1383,2305,9548,9642,22210,25619,29873,29921,30017,30402,30456,30557,30864,30964,33187,37330,37364,41383|93,0:9296,9390,24615,28121,28169,28265,28650,28704,28805,29112,29212,31435,35884,35918|94,0:1919|96,0:1754|99,0:750,834,1017,3028,4469,4537,4688,6316|100,0:2227,2326|102,0:2442,2515|105,0:7792|108,0:1192|115,0:12081,12695|119,0:8115,8729|120,0:1508,2122|125,0:1929|128,0:3469|129,0:3613,3663|131,0:3701,3721,3881,3904|139,0:3075,3131|141,0:139,379,458,573,955,1120,1723,2361,2828,2901,2962,3157,3198,3246,3316,3450,3493,4231,4508|154,0:762|157,0:1181,1657|158,0:926,1207,1634,1655,1847|160,0:1988|161,0:1919|162,0:525,825,3982,4076,13794,14703,14751,14847,15807,15878,15962,15989|163,0:2695|164,0:1808,1944,2302,2376,2619,2757,2966,3044,5065,5123,5195,5249,5649,5712,6000,6067,6730|165,0:1342,3011|167,0:2564,3740,9237,9609|168,0:2384,5568|169,0:1085,1102,2089,2564,2582,3542,3865|170,0:365,1636,3247|171,0:2363,2407,2674,2736,4213,4261,4511,4577,6487,6504,7863,7881|173,0:966,1384,1447,2611,2977,3044|174,0:2370,2420,4006,4060|175,0:2558,2602,3811,3859,7294,7338,9272,9320|176,0:1075,2487,4585,6015|177,0:1042,2218,13116,13146,13799,14038,14132,18333,18353,19830,19843,19852,20693,20719,21560,21580,22521,22534,22543,23566,23586,24986,25006,26342,26368,27424,27444,28163,28189,29193,29213,30083,30103,31769|187,0:1244,7456,7490,7609,7633,7698,7866,7902,7960,7994,8221,8247,8980,9070,9232,9560,9817,9950,10526,12144,13452,27821,28239,38961,39030,39129,39179,39220,40788,40910,40944,41014,41041|190,0:2374,3221|191,0:8675,10173,10208,10254,10302,10513,10548,10594,10642|192,0:17653,17662|195,0:4849,5249,5352,5457|197,0:331|202,0:7872,20649,22521,24406,24418,26191,26203|204,0:4260|210,0:351,6751,6883,6919|212,0:232,1761,1789,1831,1944|215,0:3574,3615,3688,3782,3930,4146,4268,4477,4703,4826,10694,10728,19570,20479,20527,20623|220,0:678,1069,3712,3753,3826,3920,4068,4284,4406,4615,4841,4964,10907,10941,19727,20636,20684,20780|231,0:4206,4247,4320,4414,4562,5129,21025,21934,21982,22078|238,0:1451|241,0:4111,4205,13388,14297,14345,14441,15402,15473,15557,15584|247,0:4941,5035,12904,14550,14598,14694|251,0:6102,6196,11128,15701,16610,16658,16754|255,0:4086,4180,8292,9201,9249,9345|256,0:3960,3970,6282|259,0:329,350,1255,1354,1410,1543,1627,1717,1722,1728,1738,2167,2249,2552,2667,3209,3336,3852,3923,4388,4547|261,0:271,747,4074|263,0:1849|271,0:2930,2971,3044,3138,3286,3847,18545,19454,19502,19598"/><wd nm="sizebaralpha" rd="177,0:12298"/><wd nm="sizebarcolor" rd="177,0:12127"/><wd nm="sizebarthickness" rd="177,0:12210"/><wd nm="sized" rd="17,0:656,848,1582,2158,3966,4047,5929|31,0:4544|33,0:312,1264,2668,2765,3788,3842,8087,10518,11119,12412,13079|40,0:10972|54,0:3208|57,0:3952|60,0:4471|68,0:3245|88,0:9141|89,0:8998|90,0:9594|91,0:9573|92,0:9688|93,0:9436|100,0:2377|141,0:4372,4493|154,0:10668|162,0:4122|177,0:14178|187,0:13989|191,0:394,9979,9987,10059|192,0:18246,18257,18265|193,0:3424|201,0:405,2855|215,0:3828|220,0:3966|231,0:4460|241,0:4251|247,0:5081|251,0:6242|252,0:80|255,0:4226|271,0:3184"/><wd nm="sizes" rd="17,0:3997,4879|33,0:13136|40,0:3933|61,0:1057|141,0:2862,2993,3123|187,0:7666,8746,8773,9327,13423|190,0:488,3172|191,0:10024|192,0:18129|201,0:386"/><wd nm="sizeto" rd="192,0:18080,18318,18346|193,0:2455|194,0:2761,2930,3219,3392|195,0:4878,4965,5051,5124,5333,5438,5605"/><wd nm="sizing" rd="17,128:20,37,153,714,806,989,4477,5992,6360,6416,6588|31,0:4916,5141,5474,5700|33,128:18,35,60,252,488,626,674,1127,1319,1570,2902,4071,4624,4697,4819,5441,5515,5651,5674,9782,12274,17091,17787,17921|37,0:8878,9098,9288,9406,9694,10187,10296|40,0:10863,11121,11185,11310|46,0:373,593,783,903,1328,1590,2119,2263,3951,4365,4868,4986|54,0:3619,3856,4181,4419|68,0:3605,3850,4178,4424|141,0:2759,4316|177,0:12190,12277,12364|187,0:8044,8072,9382,9768,9895,10013,11035,11154,12083,12779,13880,14138,14202,14327,16902,40650,40858|190,0:3193|215,0:4179,4417,4736,4975|220,0:4317,4555,4874,5113|231,0:4825,5069,5395,5640|271,0:3546,3787,4110,4352"/><wd nm="sjavascriptcall" rd="103,0:1475,1574,1681"/><wd nm="sk" rd="7,0:2740,2747,2817|8,0:284,2212,2370|18,0:2819|29,0:2290|31,0:9822|47,0:514|112,0:603,827,2313,2633|113,0:330|116,0:1559,1888,2790|119,0:6177|124,0:885|128,0:2696|135,0:3389|137,0:370,396|138,128:75,109,367,595,14491|145,0:1364,1577|147,0:3078|153,0:516|155,0:3223|157,0:3458|162,0:5691|163,0:266,286,1633,2211,2221,2276,2552,2569,2762,2839,3050,3245,3386,3415|164,0:434,480,3143,3218,3235,3278,3310,3370,3448,3467,3484,3524,3724,3762,3835,4018,4049,4093,4125,4192,4232,4328,4358,4386,4560,4589,4694|165,0:329,1708,1753,1798,1843,1888,1933,1978,2023,2068,2113,3320,4095,4107,4253,4277,4305,4329,4470,4545|167,0:2930,2966,3002,3038,3074,3110,3146,3182,3218,3254,4049,9979,9994,10201,10237,10273,10309,10345,10381,10417,10453,10489,10525,10576,11002,11065,11117|168,0:2730,6013,6047,6055,6168,6276,6742,6818,6870|169,0:1081,1262,1349,1435,1524,1611,1699,1785,1873,2559,2724,3651|170,0:239,520,555,639,719,2002,2047,2092,2137,2182,2227,2272,2317,2362,2407,3556,4239,4252,4450|171,0:104,742,850,923,1003,1104,1404,1416,1562,1613,2884,2964,3045,3127,3215,3306,3388,3468,4699,5612,5632,6483,6676,6776,6874,6976,7075,7176,7274,7375,7858,8036,8937,9005,9074,9136,9180|172,0:658,1869,1904,1943,1970,2565,2916,3066,3117|173,0:1659,1695,1731,1767,1803,1839,1875,1911,1947,1983,3214|174,128:11,34,126,188,221,248,268,285,340,393,477,541,626,687,830,1364,1491,1547,1594,1655,2867,2941,2977,3013,3049,3085,3161,3197,3233,3269,3305,3341,4438,5045,5102,5322,5342,5419,5472,5710,5750,5775,5805,5967|175,0:1234,1309,2832,2898,2964,3025,3091,3157,3226,4068,4691,5025,5131,5792,6086,6172,7583,7660,7737,7824,7908,7992,8071,8150,8235,8320,8410,9545,10894,11005|176,0:1441,1477,1513,1549,1585,1621,1657,1693,1729,1765,2796,4951,4987,5023,5059,5095,5131,5167,5203,5239,5275,6324|177,0:332,1408,1444,1480,1516,1552,1588,1624,1660,1696,1732,2527,3618,3734,3836,6412,6534,6652,6669,6694,6740,6800,6852,6867,6951,12423,12535,12656,12824,13280,14783,17437,22064,23091,23111,23234,23319,23415,23473,23506,23555,23599,23641,23676,23758,23816,23870,23953,24043,24102,24119,24141,24270,24346,24404,24514,24602,24647,24715,24741,24824,24931,24976,25016,25057,25091,25177,25234,25282,25334,25385,25430,25544,25628,25715,25779,25844,25905,30922,30996,31054,31170,31246,31587,31603,31936,31982|182,0:2267|190,0:3421,7326,7353,7427,7705,7756|199,0:4259|221,0:4808"/></pk>