<?xml version="1.0" encoding="UTF-8" standalone="no"?>
<pk><wd nm="stomized" rd="19,0:4423|31,0:6183|32,0:1333,2095|34,0:1801,2430|36,0:840|39,0:737,1248|41,0:1945,2617|42,0:2138|44,0:729,2005|54,0:4944|60,0:3890|68,0:4723|88,0:8334|89,0:7636|90,0:8276|91,0:8255|92,0:8485|93,0:7678|105,0:13235|111,0:1181|115,0:13038|120,0:2639|121,0:210,760|134,0:210,760|146,0:5848|157,0:179|162,0:3541|163,0:2156|169,0:3814,3940|172,0:2169,3022|174,0:977|177,0:8250,20553|202,0:13448|215,0:5330|220,0:5518|231,0:6209|237,0:143|241,0:3670|247,0:4247|251,0:5661|255,0:3384|256,0:607|257,0:139|258,0:154|260,0:118|261,0:8224,8333|262,0:124|263,0:2663,2772|271,0:4827"/><wd nm="stomizing" rd="18,0:5902|32,0:1224|34,0:1670|41,0:1804|42,0:661|44,0:670|55,0:983,1891|61,0:160,880|110,0:1321|111,0:1732|115,0:10483|119,0:7010|126,0:1957|164,0:346,371,523,1239|169,0:3871|174,0:311,5300|212,0:191,1391|264,0:165,694"/><wd nm="stone" rd="163,0:2656,2752|170,0:326,422,500,539,593,656,732,777,2470,2558,4016,4369,4418,4461,4509,4580,4660,4715,4755,4783,4801|177,0:463,31467,31679,31730,31879,31951,32045,32097,32206,32253,32294,32343,32397,32441,32545"/><wd nm="stones" rd="163,0:275,2369,2381,2518,2586|170,128:19,37,49,186,256,843,2459,2651,4004,4275,4310,4339,4988|172,0:2196,2222,2320|177,0:451,3927,3944,24460,31455,31485,31553,31620,32004"/><wd nm="stop" rd="27,0:693,1834|31,0:10913,11170|53,0:567,930|54,0:6789,7046|67,0:571,934|68,0:9240,9497|74,0:441,4634|84,0:1387,1506|88,0:7757,8026|89,0:7059,7328|90,0:7698,7967|91,0:7678,7947|92,0:7908,8177|93,0:7101,7370|94,0:1531,1860|108,0:1567|138,0:6095|139,0:1976|187,0:29646,34130,34149,34198,34277,34303,34322|190,0:308,4785,4821,4984,6085|206,0:8698|209,0:351,4938,4957,5006,5085,5111,5130|215,0:9824,10081|219,0:564,927|220,0:10035,10292|228,0:697,1863|231,0:10817,11074|242,0:1050,5246,6217,7503|243,0:4519,4648|256,0:9067|270,0:575,938|271,0:9211,9468"/><wd nm="stopmargin" rd="70,0:3532|88,0:36567|89,0:35140|90,0:36590|91,0:40133|92,0:36852|93,0:35406"/><wd nm="stopped" rd="23,0:1124|50,0:720|64,0:728|73,0:505|77,0:752|127,0:5995|216,0:719|225,0:1174|267,0:734"/><wd nm="stopping" rd="27,0:1787,1959|53,0:883,1055|67,0:887,1059|74,0:4587,4759|190,0:4903|219,0:880,1052|228,0:1816,1988|242,0:5199,5371,7456,7628|270,0:891,1063"/><wd nm="stops" rd="23,0:1058|50,0:654|64,0:662|73,0:439|77,0:686|206,0:8703|216,0:653|225,0:1108|267,0:668"/><wd nm="stopupdate" rd="23,0:1030|27,0:1941|50,0:626|53,0:1037|64,0:634|67,0:1041|73,0:411|74,0:4741|77,0:658|190,0:6046|193,0:2546|203,0:2766|216,0:625|219,0:1034|225,0:1080|228,0:1970|242,0:5353,7610|267,0:640|270,0:1045"/><wd nm="storage" rd="7,0:4610|76,0:1059|142,0:490"/><wd nm="store" rd="24,0:538|51,0:535|58,0:537|65,0:539|80,0:564|86,0:1025|88,0:7583|89,0:6885|90,0:7524|91,0:7504|92,0:7734|93,0:6927|142,0:978|146,0:10095|156,0:402|160,0:537|168,0:536|217,0:534|226,0:547|240,0:538|244,0:940|248,0:536|263,0:1420|268,0:542"/><wd nm="stored" rd="76,0:1039|145,0:233|149,0:2324,3388|150,0:2532|179,0:739|196,0:2261"/><wd nm="stores" rd="126,0:4405|138,0:4770,6438,8813,9797|194,0:2181|197,0:1883"/><wd nm="storical" rd="70,0:1648,4015,4275|72,0:2646,2859|74,0:458,4414|75,128:27,49,211,284,323,368,2135,2412,2592,2701,3025,3215|76,0:1110|84,0:295|86,0:621|187,0:35827,36087|242,0:489,1067,5026|243,0:680,1271,1602,2359,4862|244,0:536"/><wd nm="storing" rd="86,0:840|244,0:755"/><wd nm="storm" rd="165,0:1555,3199|167,0:1233,2777,3928,9450,9797|168,0:2592,5776|170,0:1849,3435|173,0:1179,2799|174,0:2714,4317|176,0:1288,2675,4798,6203|177,0:1255,2406"/><wd nm="storted" rd="33,0:17259|37,0:9847,9933|46,0:1743,1829,4518,4604|154,0:5330|187,0:12251|192,0:7350|205,0:3671,10492|206,0:2396|208,0:5188|210,0:3990"/><wd nm="stortion" rd="33,0:2257,3091,3921|187,0:10696"/><wd nm="story" rd="31,0:14533|54,0:9237|68,0:10812|88,0:13925,19218|89,0:13940,19232|90,0:14378,19670|91,0:15491,23000|92,0:14265,19502|93,0:14262,19498|190,0:35|215,0:12001|220,0:12214|231,0:13456|235,0:1762|236,0:1865|261,0:4383|271,0:11019"/><wd nm="stperdownload" rd="152,0:1790"/><wd nm="str" rd="9,0:3882"/><wd nm="stracting" rd="59,0:230"/><wd nm="straight" rd="105,0:3002"/><wd nm="straightaway" rd="8,0:168"/><wd nm="strain" rd="74,0:2349|76,0:1270|242,0:2961"/><wd nm="strained" rd="17,0:795|33,0:331,2846,3022,3221,3481,3946,17708|37,0:9541,9595,9735,9874,9980|46,0:1428,1491,1631,1770,1877,4203,4266,4406,4545,4652|187,0:12700"/><wd nm="strainedscale" rd="33,0:2436,3285,3379,3433,3578,3641|37,0:9562|46,0:1449,4224|187,0:10875"/><wd nm="strainer" rd="94,0:2392"/><wd nm="straints" rd="0,0:5690|8,0:3428|31,0:20903|54,0:15687|57,0:13811|60,0:14276|68,0:17262|88,0:24192|89,0:23205|90,0:24122|91,0:27555|92,0:24475|93,0:23471|162,0:12649|177,0:10670|187,0:37722|215,0:18427|220,0:18584|231,0:19882|241,0:12244|247,0:11760|251,0:14557|255,0:7148|271,0:17400"/><wd nm="stransparent" rd="192,0:11202"/><wd nm="strate" rd="33,0:6329|151,0:227|167,0:864|178,0:292|187,0:5362|195,0:1325|196,0:7409,9881,11410,12147|198,0:2526,4531|238,0:101|263,0:256"/><wd nm="strated" rd="63,0:390|266,0:386"/><wd nm="strates" rd="85,0:1789|155,0:5317|187,0:6350|198,0:1251"/><wd nm="strating" rd="163,0:1043"/><wd nm="stration" rd="103,0:1051,2893|180,0:943,1361|192,0:4689|200,0:437,1204,1240|201,0:830,3029"/><wd nm="strations" rd="142,0:1462"/><wd nm="strchartype" rd="192,0:19685,19826,19996,20160"/><wd nm="strcsv" rd="192,0:14991"/><wd nm="strdata" rd="23,0:343,352|50,0:332,341|64,0:340,349|73,0:201,210|77,0:424,433|78,0:321,360,1079,1153,1829|216,0:331,340|225,0:336,345|267,0:346,355"/><wd nm="stream" rd="9,0:682,821,2622,2946,3097,3207,3425,3493,3518,3635,3743,3837,3936|27,0:1689,2832|31,0:10179|53,0:1928|54,0:6055|67,0:1932|68,0:8506|72,0:4718,5756,6376,7334,8015,8870,10426|73,0:249,269|77,0:472,507|82,0:2718|83,0:2511,2960|86,0:245,1479,1535|88,0:13050|89,0:13065|90,0:13503|91,0:14616|92,0:13390|93,0:13387|94,0:7423|96,0:1899|127,0:3121|128,0:1663|148,0:5358|159,0:304|178,0:985|180,0:559|190,0:5250|192,0:12308|206,0:7911,7975,8660,9007,9017|215,0:9090|219,0:1925|220,0:9301|228,0:1712,2861|231,0:10083|232,0:604|234,0:1996|235,0:108,249,337,376,1833,2495,3961,4288,4731|236,0:570,3090|242,0:7358|244,0:246,1394,1450|270,0:1936|271,0:8477"/><wd nm="stream:string" rd="206,0:7856"/><wd nm="streamed" rd="25,0:311|31,0:14737,14998,15235|54,0:9441,9702,9939|68,0:11016,11277,11514|81,0:312|88,0:19422,19664,19901|89,0:19436,19678,19915|90,0:19874,20116,20353|91,0:23204,23446,23683|92,0:19706,19948,20185|93,0:19702,19944,20181|94,0:520|215,0:12205,12466,12703|220,0:12418,12679,12916|231,0:13660,13921,14158|232,0:120,452,544,2024|234,0:371,789,1167,1693|235,0:1021,1339|236,0:881,980,1154,2078,2339,2576|271,0:11223,11484,11721"/><wd nm="streamfusioncharts" rd="210,0:5512,5649,5786"/><wd nm="streamfusionchartsdata" rd="187,0:29811,29985,30232,30376,30681,31045,31181,31373,31547,31845,32232,32785,33062,33507,33998,34253,34486,34714|206,0:7833,8071,8111,8153,8212,9079,9132,9216|209,0:516,793,1040,1184,1489,1853,1989,2181,2355,2653,3040,3593,3870,4315,4806,5061,5294,5522"/><wd nm="streaming" rd="25,0:81|27,0:2148|31,0:13788|40,0:6265,6435,6597,6757,6892,7013,7122,7221|53,0:1244|54,0:8492|67,0:1248|68,0:10067|69,128:5,3702,4360|70,128:5,478,2190,3083,3621,5402|71,128:5,108,3484|72,128:5,10803|73,128:5,65,1082|74,128:5,97,1032,1251,4919,5180|75,128:5,3188|76,128:5,287,1436|77,128:5,88,389,2175|78,128:5,84,2040|79,128:5,84,1037,2044,6619|80,0:4,39,1858,3220,4094|81,128:5,82,529,766|82,128:5,79,3346,4196|83,128:5,3132|84,128:5,35,62,216,478,609,863,888,1855|85,128:5,66,399,1209,1625,2341|86,128:5,3676|87,128:5,327,2368,3336|88,128:5,12254,12863,18473,47132|89,128:5,12116,12878,18487,43703|90,128:5,12707,13316,18925,48431|91,128:5,13820,14429,22255,52061|92,128:5,12594,13203,18757,47418|93,128:5,12342,13200,18753,43969|180,0:1579|181,0:638|184,0:2306|185,0:663|186,0:184|187,0:29659,29689,34174,34342,34406,34586|190,0:4592,5437|196,0:9289,10107,10355|206,0:8719,8817|209,0:364,394,4982,5150,5214,5394|215,0:11256|219,0:1241|220,0:11469|228,0:2177|231,0:12711|232,0:2158|234,0:74|235,0:14,43|242,0:287,390,438,562,701,1641,1861,5531,5780,7818|243,0:571,608,629,1066,2331,4150,4749,4832|270,0:1252|271,0:10274"/><wd nm="streamline" rd="159,0:261"/><wd nm="streamlined" rd="157,0:346,3051,3091|158,0:98|159,0:73,1055,1254|161,0:95,204,1690|162,0:9777,10037|190,0:7896"/><wd nm="streamlineddata" rd="105,0:13106|161,0:851,1242,1612|162,0:9723|202,0:13320"/><wd nm="streamlining" rd="159,0:846"/><wd nm="streams" rd="94,0:262|119,0:5877,6053|128,0:1564,1607|190,0:5871|210,0:7769|232,0:1707"/><wd nm="streamurl" rd="27,0:2694,2881,3081,3655,4278,4733,5243,5360|31,0:10041,10228,10428|45,0:1093,2492|53,0:1790,1977,2177,2748,3296,3676,4088,4193|54,0:5917,6104,6304|67,0:1794,1981,2181,2631,2777,2925,3329,3434|68,0:8368,8555,8755|71,0:1945,2050|72,0:1393,1797,2349,3003,3164|75,0:466,1301|80,0:1994,3355,3531,3706|82,0:619,1067|86,0:366,443,1991,2158,2244|87,0:836,1318|88,0:1173,2021,12912,13099,13299|89,0:1274,2050,12927,13114,13314|90,0:1173,2003,13365,13552,13752|91,0:1004,1809,14478,14665,14865|92,0:1228,2136,13252,13439,13639|93,0:1316,2092,13249,13436,13636|96,0:1519|98,0:188,293|191,0:9190,9738|215,0:8952,9139,9339|219,0:1787,1974,2174,2745,3293,3673,4085,4190|220,0:9163,9350,9550|228,0:2723,2910,3110,3682,4314,4777,5293,5398|231,0:9945,10132,10332|235,0:424|242,0:100|243,0:2202,2545|244,0:353,1906,2060|270,0:1798,1985,2185,2635,2764,2894,3306,3411|271,0:8339,8526,8726"/><wd nm="strendzone" rd="87,0:2954,3058,3185|88,0:45741|89,0:42312|90,0:47038|91,0:50867|92,0:46028|93,0:42579|176,0:5383,6745,6856|177,0:33656|245,0:2197,2282|247,0:18300|249,0:4330,4407|251,0:20126"/><wd nm="strength" rd="0,0:1074,1766|99,0:3273,6519|257,0:1332,1344,3315,3339,3354,3429,3486,3527,3536,3553|260,0:713,725,1862,1906,1979,2061,2209,2349,2358,2375,2421,2451|262,0:860,872,2703,2734,3005,3014,3031,3112,3213,3292,3349,3365"/><wd nm="stretch" rd="0,0:388,2852,5359,5611,5932|31,0:20726,20825|32,0:2857|34,0:3133|41,0:3482|46,0:7040|54,0:15510,15609|57,0:13634,13733|60,0:14099,14198|68,0:17085,17184|88,0:24015,24114|89,0:23028,23127|90,0:23945,24044|91,0:27378,27477|92,0:24298,24397|93,0:23294,23393|162,0:12472,12571|177,0:10493,10592|187,0:37308,37486,37523,37643|215,0:18250,18349|220,0:18407,18506|231,0:19705,19804|241,0:12067,12166|247,0:11583,11682|251,0:14380,14479|255,0:6971,7070|271,0:17223,17322"/></pk>