<?xml version="1.0" encoding="UTF-8" standalone="no"?>
<pk><wd nm="tfillmix" rd="18,0:4404,4472,4552,4805,4960,5091,5202,5584,5767|31,0:13386"/><wd nm="tfillpercent" rd="55,0:1725,1745,1779,1799|57,0:10585,10675|60,0:11054,11143"/><wd nm="tfillradius" rd="18,0:5818"/><wd nm="tfillratio" rd="18,0:5137,5248,5619,5801|31,0:13445|89,0:20815|93,0:21081"/><wd nm="tfilltype" rd="18,0:5544,5729|31,0:13293"/><wd nm="tfit" rd="148,0:6632|154,0:5272|192,0:7292|205,0:3615,10436|206,0:2340|208,0:5132|210,0:3934"/><wd nm="tflashplayer" rd="96,0:4550|148,0:1704,4597"/><wd nm="tflashversion" rd="154,0:5445,5596|192,0:7450,7601|205,0:3786,3936,10607,10758|206,0:2511,2662|208,0:5303,5454|210,0:4105,4256"/><wd nm="tfontstyle" rd="259,0:1501,1587,2510,2627,3167,3296,4346,4507|261,0:229,511,707,953,1674,2444,2580,2732,3579,3731,6204,6388,6598,6992,7064"/><wd nm="tform" rd="139,0:1751"/><wd nm="tformat" rd="97,0:1487,1726|113,0:1759|115,0:10292|123,0:4172|131,0:907,1353|132,0:601,903,1427|191,0:11252|192,0:18697,21681,21809,21822,21989,22158,22675|193,0:1771"/><wd nm="tformat:string" rd="192,0:22247"/><wd nm="tformats" rd="94,0:7069|122,0:363|130,0:409,775|136,0:363|191,0:11265"/><wd nm="tforms" rd="184,0:3206"/><wd nm="tframe" rd="102,0:2420,2605"/><wd nm="tfromid" rd="23,0:1781,1832,1875|38,0:577,628,671|50,0:1377,1428,1471|64,0:1385,1436,1479|192,0:917,1048,1203,23539|193,0:1082|196,0:8527,8692|197,0:2569,2608,2758,2781,3007|203,0:2037|216,0:1376,1427,1470|225,0:1831,1882,1925,2544|233,0:702,753,796|267,0:1391,1442,1485"/><wd nm="tfunction" rd="144,0:1796,2564|192,0:21532,22631"/><wd nm="tfunction:function" rd="192,0:22223"/><wd nm="tfunctionname" rd="107,0:1997"/><wd nm="tfusioncharts" rd="154,0:2987,3341,3508,6478,7278,7741,8204,8374,9142|187,0:25131,25349,25650,26167|205,0:381,896,963,1008,1707,1926,4173,4307,4647,5009,5399,6560,7327,7999|206,0:367,2914,3606,5336|208,0:3023,3283,3452,6586,7403,7878,8458,9294"/><wd nm="tglobal" rd="127,0:1465,1549"/><wd nm="tglow" rd="260,0:1189,1257,1542,1630,2014,2085,2165,2228"/><wd nm="tgoog" rd="82,0:2217,2232,2318,2335,2463,2478,2499|83,0:1229,1244,1426,1443,1572,1587,1608,1650,1665,1686,1728,1743,1764"/><wd nm="tgradientcolor" rd="88,0:20684|89,0:1464,2260,21049|92,0:1495,2429,20968|93,0:1489,2283,21315"/><wd nm="tgresql" rd="142,0:460|185,0:1656"/><wd nm="th" rd="0,0:1074,1766,2107,2223,2403,2777,5433,5852|1,0:1265,3650,4656|2,0:83,241,1513|3,0:379|4,0:111|5,0:339,2672,2926|6,0:616,959,2074,2475|7,0:157,391,1219,1597,3512,5026,5070,5103,5144|8,0:3388|9,0:421,1391,1805,2531,4169|10,0:350,636,921,995,1278,1562,1838,1925,2197,2481,2758,2845,3119,3404,3680,3767,3958,4323,4607,4883,4970,5155|11,0:550,819,1083,1171,1502,2110,3436,3864,4153,4467,4787,4903,5240,5524,5800,5887|12,0:398,446,1416,1942,2038,2623,2998|14,0:1930,2519|16,0:162,269,1718,2439,3004,3793,4017,4527|17,0:207,817,821,1005,1141,1279,1337,1392,1463,1695,1888,1974,2065,2128,2334,3806,3814,3880,4329,4615,4682,4916,5090,5297,5397,5470,5593,6330|19,0:4471,4792|20,0:210,219,758,1537,1749,1758,1809,1856,1870,1901,1914,2018,2183,2232,2537,2646,2723,2841,2919|21,0:2375,2539,3130,3544|22,0:1317,1323|23,0:213,2182,2802|24,0:267,478,927,2615,3431,3482|26,0:1678|27,0:1752,2581,2732,4984,5058,5062,5236,6651|29,0:326,530|30,0:131,674,1896,1971,3911|31,0:4363,4684,4727,4839,4848,4986,5038,5053,5396,5597,5612,6762,9460,9897,10079,14097,14147,14212,16936,16965,20362,21058,26509,26534,26589,26613,28125,28200,29204,29287|32,0:580|33,0:463,548,729,1450,2350,3184,3678,4301,5103,5626,5727,5804,5997,6079,6392,6464,6594,6646,8306,9759,10733,11799,11994,12134,12192,12510,12613,12657,12848,13039,13241,13281,13401,13468,13638,13726,13799,13866,14099,14795,14806,16018,16030,16736,17403,17485|35,0:851,945|36,0:1619,1693,1733,1755|37,0:526,604,799,1766,1777,3391,3403,6666,6909,8694,8713,8971,9015,9069,9168,9222,9237,9505,9623,10326,10450,11015,11138,11209,11242,11299,11498|38,0:200,279,1171,1800,2474|39,0:722,2545|40,0:1423,1434,1499,1510,1575,1586,2509,2522,2598,2611,2687,2700,3294,3384,3680,4328,4393,5142,5506,5517,7080,7092,7276,7286,7350,7369,7828,8048,8059,8787,8799,8843,8853,8889,8908,10943,11225|41,0:100,648,676,939|42,0:1894|43,0:1139|44,0:1287,1302,1409,1432,1451,3858,3885|45,0:3659|46,0:209,228,466,510,564,663,717,732,1007,1278,1411,1519,2293,2413,3407,3553,3583,3605,3763,3782,4166,4294,5016,5140,7637,7974,8048,8086,8108,10071,10098|47,0:989,1440|50,0:202,1774|51,0:264,475,924,2459,3062|53,0:1677,1828,4081,5484|54,0:3027,3395,3438,3542,3551,3689,3741,3756,4103,4304,4319,5523,5955,8801,8851,8916,11714,11743,15146,15842|55,0:1646,1840|57,0:5361,8138,8167,11307,13270,13966|58,0:266,477,926,2545,3316|59,0:226|60,0:5882,6153,6472,8600,8629,11084,11175,11774,13735,14431|61,0:2382|64,0:210,1786|65,0:268,479,928,2320,2644|66,0:368,748|67,0:1681,1832,3322,4725|68,0:3064,3385,3428,3525,3534,3675,3735,3750,4097,4309,4324,5302,7424,7731,7993,8406,10376,10426,10491,13289,13318,16721,17417|69,0:2610,3208|70,0:2239,2755,3179,3216,3321,3754,3992,4252,4384|71,0:100,527,647,1218,1621,1938,3341|72,0:884,2900,3016,6459,6494,6501,8106,8178,9799,9920,10052|74,0:2252,3286,4563|75,0:113|76,0:1106|77,0:280|78,0:1002,1012|79,0:801,2520,3615,4619,4925,5006,5627,5953|80,0:293,504,953,3062,3544,5789|82,0:2842,3161,3937|83,0:374,685,727|84,0:949,1061|85,0:1165,1567|86,0:233,381,457,1184,2258|87,0:136,1791,2655,3132|88,0:847,4968,8913,9840,9920,11257,12320,12399,12664,12950,16197,16226,18782,18832,18897,20535,20585,21753,21786,23651,24347,27123,27243,27922,28023,28423,28526,31440,31509,33064,37882,37975,38122,39118,39222,40901,40934,42341,44574,45492,46158,46263,46443|89,0:853,4417,8136,8161,8374,8412,8770,9697,9777,11119,12182,12261,12526,12965,16212,16241,18796,18846,18911,20630,20680,22664,23360,26136,26256,26687,26790,29704,29773,31328,34075,36455,36548,36695,37436,37540,39448,41145,42063,42729,42834,43014|90,0:847,4910,8855,9090,10293,10373,11710,12773,12852,13117,13403,16650,16679,19234,19284,19349,21006,21100,21787,21820,23581,24277,27054,27174,27853,27954,28354,28457,31460,31529,33084,37905,37998,38145,39141,39245,40876,40991,41320,41353,42182,43114,45305,45871,46789,47455,47560,47740|91,0:876,4889,8834,9069,10309,10390,10432,10513,12625,13886,13965,14230,14516,17763,17792,21333,21362,22564,22614,22679,24336,24430,25116,25149,27014,27710,30486,30606,31285,31386,31786,31889,35003,35072,36627,41447,41540,41687,42683,42787,44591,44706,45035,45068,45897,46829,49020,49586,50618,51284,51389|92,0:884,5120,9064,10387,10467,11597,12660,12739,13004,13290,16474,16503,19066,19116,19181,20819,20869,22036,22069,23934,24630,27405,27525,28204,28305,28705,28808,31722,31791,33346,38167,38260,38407,39403,39507,41186,41219,42626,44861,45779,46445,46550,46730|93,0:895,4459,8178,8203,8416,8454,8812,10135,10215,11345,12408,12487,12752,13287,16471,16500,19062,19112,19177,20896,20946,22930,23626,26402,26522,26953,27056,29970,30039,31594,34341,36721,36814,36961,37702,37806,39714,41412,42330,42996,43101,43281|94,0:1346,1947,2038,2152,2236,2466,2699,3519,3581,3945,4252,4848,6565,8308,9359|95,0:434,450,1112,1231,1814,2935,3207,4206|96,0:876,1038,2140,3626,3694,3894,3976,4226,4447,4938,5448|97,0:2056,2333,4163,5337,7758,8350,8501|98,0:181,1584|99,0:967,1240,1367,1461,1485,1610,1733,1842,1945,3273,3320,4651,4869,4980,5059,5082,5191,5298,5391,5478,6519,6563,7306,7434,7508,7557|100,0:171|102,0:324|103,0:2661,6265|104,0:728,3895|105,0:618,703,863,1873,2196,2258,2750,3687,4945,7133,9441,13183,13231,13619,13833,13850,14629|106,0:725,2902,3800,4862|107,0:1703|108,0:205,279,338,666,869,891,939,1090,1108,1547,2444,2522,2654,2786,2918,3050,3182,3351,3438,3569,3700,3831,3962,4093|109,0:1385,1400,1475,1541,1786,2024,2481,3091,3250,3719|111,0:421|112,0:1280,1340,2160,4510,4640,4750,4800|113,0:1247,1430,2024,3044,3521,3651,3761,3811|114,0:791|115,0:139,491,1247,4566,5013,5143,5280,5330,5620,7793,8176,8306,8416,8466,8907,11347,11477,11609,11659,12341|116,0:1048,1108,1264,3284|117,0:1228,1260,1471,1716,1835,4163,4271,4407,4490,4614,4703,7309,7359,7906|118,0:612|119,0:155,501,2564,2723,4903,5955,6554,7644,7694,8375,9178,9292|120,0:395,411,1037,1087,1768,2583|123,0:179,742,910,1447|124,0:1280|125,0:3035,3108|126,0:414,1739,2855,3467,3571,3614,4005,4047,4098,4261,4274,4308,4331,4361|127,0:66,134,2578|128,0:112,168,1625,1721,2171,8103,8148|129,0:450,562,1904,2408|130,0:483,733,1002,1105,1112,1229|131,0:1319,1444,1490,1507,1608,1716,1861,3927,3947,4993,5025|132,0:1042,1224,1701|133,0:1548,2960,5150,7811,8010|135,0:537,1514,1569|137,0:470|138,0:815,970,1387,1417,1903,2212,2677,3371,3836,3940,3983,4370,4412,4463,4626,4639,4673,4696,4726,5722,5735,5771,5807,5822,5867,6008,6356,6385,7825,8654,8714,8727,8775,9629,9642,9676,9695,9734,11260,11295,11363,11484,12163,12915,12975|139,0:865,3159,3374|140,0:345,393,966|141,0:160,276,489,683,723,771,985,1465,1512,1599,1838,2102,2143,2301,2494,4152,4188,4207|142,0:123,416|144,0:1314,1655,2171,2445|145,0:1032,2295,2422,2504,2553|146,0:194,392,1410,1448,3677,5079,5748,7909,8420,8684,8738,8822,9151,9457,10249,11138,11180,11924,12505,12801,12982,13282|147,0:353,689,2277,4215,4243,4266,4345,4371,4425,4659,5009,5086,5752,6333,6629,6810,7110|148,0:868,1086,1347,1508,1583,1964,2170,2249,2284,2683,2748,3038,3392,3637,4093,4476,4727,5336,5451,5549,5705,5803,5920,5939,6006,6112,6335,7100|149,0:2265|150,0:486,571,911,1044,1633,2012,2497,4889,4914,5899,5924,6613,7362|151,0:483,3956,4052,4164,4282,4395,4516,4555,6508|152,0:2213,2313,2400,2718|153,0:2435,2580,2957|154,0:95,2038,3062,3314,3435,3840,4069,4075,4144,4174,5592,6533,7316,7779,8242,8737,8995,9717,9910|155,0:420,864,893,6266|156,0:353,633,1856|157,0:175,315,530,3020,3138,3714|158,0:208,1950,2277,2492|159,0:892,1036,1078,1124,1603|160,0:266,477,926,2515,3471|161,0:267,602,977,1371,1570,2037|162,0:5042,5500,7401,7430,12108,12804,17213|163,0:540,928,1380,1452,1593,2308|164,0:4066,4188,6233,6325,6430,6472,6571,6617,6798,6836,6862,6892,6918,6947|165,0:4707|166,0:103,1468,1672,1696,1789|167,0:6116,8296,10075|168,0:265,476,925,3457,6981|169,0:84,621|170,0:714,4385|171,0:248,1333,1750,1845,3638,3737,5616,8951,9009,9140|172,0:882,2078,2263,2849,2924|173,0:93,3778,3908,5426,5514|174,0:292|175,0:321,1447,5002,5860,10871|176,0:6817|177,0:3844,5963,6025,6135,6228,6253,7134,10129,10825,16398,16428,18683,20373,20395,22420,28875,28897,32809,33533,33905,33996|178,0:741,1754,3450|179,0:250,3263|181,0:107|182,0:1921|183,0:2434|184,0:731|185,0:532,724,970,1344,1478,1535,1825,2596,2671,3203|187,0:1655,7297,7533,7582,7679,7787,8941,9200,9214,9582,10789,11207,11284,11477,11559,12395,12477,13960,14242,16149,16520,17251,20038,20508,22019,25436,25722,26217,26894,27196,27811,28290,28443,30299,35804,36064,36196,37595,37827,39377,40720,40792,40864,41580,41732,41908,41971,42104|188,0:517,629,834|189,0:292,441,670|190,0:590,3182,3375,4180,5945,6833,7108,7277,8240,8759|191,0:1360,4924,8986,8999,9115,10147,10153,10215,10233,10487,10493,10555,10573,11474,11482,11904,11950,11959,12495,12541,12550,13129,13175,13184,13609,13655,13664,16251|192,0:2064,2479,2593,2599,6451,6575,6581,6796,7597,15504,17850,18164,19634,23341,23987,24457|193,0:1404,1898|194,0:1213,1219,1264,1334,2543,2601,2816,2850,2869,2897,2959,3433,3517|195,0:747,3841,4795,4912,4999,5143,5475,5556|196,0:7028,7097,7186,9316,9962,10202,10571,10739,10876,10930,11088,11572,11679,11708,11813,11868,12209,12332,12491,12612|197,0:216,408|198,0:362,800,2054,2597,3128,4616|199,0:280,1217,4201,6411,8221|200,0:3475,4649|201,0:1012,1945,2459,2884,2908,4235|202,0:500,585,745,1868,2191,2258,2391,2555,3828,5073,7206,9647,13397,13444,13832,14079,14096,14188,14800,17679,18065,18839,19153,19498,20504,21003,22051,22607,22913,24052,24262,24317,24653,25837,26047,26102,26649,27853,28517,29279,29383,29824,30337|203,0:275,1753,3245,3491,3854|204,0:1322,3376,3863,4379|205,0:1794,2202,2348,2354,2423,2456,3932,4692,5054,5444,6441,7208,7870,7924,8126,9020,9166,9172,9241,9274,10754|206,0:931,1077,1083,1152,1182,2658,3001,3693,4405,5254,5566,5924,6068,6914,7145,7234,7560,10834,10875|207,0:388,890,915,1184,1685,1726|208,0:3110,3256,3379,3726,3872,3878,3947,3974,5450,6656,7453,7928,8508,9568,9777|209,0:1107|210,0:1213,2054,2574,2658,2664,2733,2769,4252,4643,5067,5469,5715,6153,6194,6248,6356,6421,6609,6685,6814,6842,6986,7004,7225,7346,8584,8781,9386,9583,9708,10352,10549|211,0:1924,2104,2285,2551|212,0:981,2744|213,0:3492|214,0:114,565|215,0:3647,3968,4011,4108,4117,4249,4302,4317,4664,4860,4875,5909,8577,8990,11565,11615,11680,14460,14489,17886,18582|216,0:201,1773|217,0:263,474,923,2534,3170|218,0:84|219,0:1674,1825,4078,5481|220,0:3785,4106,4149,4246,4255,4387,4440,4455,4802,4998,5013,6097,8219,8526,8788,9201,11778,11828,11893,14617,14646,18043,18739|221,0:1121,5619|222,0:4096,4173|223,0:2313,2480,3186,3602|224,0:627,1189|225,0:206,2230,2854|226,0:276,487,936,2625,3503,3554|227,0:78|228,0:1778,2610,2761,5028,5105,5109,5286,6689|229,0:336,535|230,0:140,684,1523,1598,3210|231,0:4279,4600,4643,4747,4756,4895,4954,4969,5316,5525,5540,6788,9618,9983,13020,13070,13135,15915,15944,19341,20037,26386,26461|232,0:477,2145|234,0:1835|235,0:1839,2455,3135,4988,5076|236,0:608,1431,1481,1546|237,0:139,392,1285,1872,2377|238,0:340,688,1053,1252,1618|239,0:196,720|240,0:267,478,927,2121,2632,3588|241,0:639,1004,5176,5614,7304,7333,11703,12399,16808|242,0:353,532,2864,3898,5175,7421|243,0:723,857,1469,1533,1993,2068,4243,4314|244,0:234,368,1099|245,0:487,551,621,767,838,1152,1179|246,0:1076|247,0:4747,4772,7073,7102,9831,11219,11915,17506,18629,18734|248,0:265,476,925,3217,3928|249,0:548,613,684,923,987,1121,1192|251,0:8234,8263,10954,10987,12628,14016,14712,19332,20455,20560|252,0:1016,1072,1123|253,0:218,553,617,687,831,902,1275,1630|255,0:3884,3909,5219,6607,7303|256,0:2814,3383,5426,6822,7039,7050,7462,7474,9360,9472,9585,9683,9758|257,0:1332,1344,1657,3253,3270,3274,3315,3339,3354,3429,3486,3527,3536,3553,3581|259,0:210,3637|260,0:713,725,1045,1804,1821,1862,1906,1969,1979,2061,2209,2349,2358,2375,2410,2421,2439,2451|261,0:2253,6033,8097,8378,8475|262,0:860,872,1205,2256,2668,2703,2734,3005,3014,3031,3053,3075,3112,3213,3292,3338,3349,3361,3365|263,0:321,730,850,2379|264,0:2489|267,0:216,1795|268,0:271,482,931,2305,2624|269,0:646|270,0:1685,1836,3299,4702|271,0:3003,3324,3367,3471,3480,3616,3672,3687,4034,4237,4252,5406,7495,7745,8012,8377,10583,10633,10698,13436,13465,16859,17555"/></pk>