<?xml version="1.0" encoding="UTF-8" standalone="no"?>
<pk><wd nm="ter&apos;s" rd="222,0:3863|223,0:3841,4601|231,0:5693"/><wd nm="ter1" rd="115,0:3882,4023,4249,10902,11043|116,0:2523|117,0:2899,3559,4282,5544,5612,7018,7756,7917|119,0:2010,2151,2441,3586,3727,4417,7431,7573|120,0:966"/><wd nm="ter2" rd="117,0:2136,2446,2913,4044,4296"/><wd nm="ter_name" rd="119,0:9115|120,0:2519"/><wd nm="ter_rle2img" rd="126,0:2948|138,0:3169"/><wd nm="ter_rle2pdf" rd="126,0:3032|138,0:3243"/><wd nm="ter_svg2all" rd="126,0:2797,3437|138,0:3313,3806"/><wd nm="teract" rd="38,0:2466|88,0:31432|89,0:29696|90,0:31452|91,0:34995|92,0:31714|93,0:29962|94,0:3511|95,0:4198|99,0:1453,5051|119,0:6546|162,0:17205|241,0:16800"/><wd nm="teraction" rd="17,0:312|23,0:5113|27,0:2008|33,0:834|50,0:3873|53,0:1104|64,0:3895|67,0:1108|74,0:4808|77,0:2005|141,0:3083|157,0:4023|185,0:3089|187,0:9786|191,0:9343|216,0:3873|219,0:1101|225,0:5090|228,0:2037|233,0:1702|238,0:1719|242,0:5420,7677|267,0:3902|270,0:1112"/><wd nm="teractive" rd="0,0:521|79,0:6400|82,0:3308,3366,3429,3984|84,0:1528|159,0:1299|163,0:2040|185,0:1407|190,0:5771,7941,8567|192,0:23286|197,0:2528|239,0:528"/><wd nm="teractivelegend" rd="82,0:4042,4073|88,0:31381|89,0:29645|90,0:31401|91,0:34944|92,0:31663|93,0:29911|162,0:17144|241,0:16739"/><wd nm="teractivity" rd="146,0:408|147,0:369|190,0:951"/><wd nm="teracts" rd="178,0:732"/><wd nm="teracy" rd="31,0:7824|68,0:6364|215,0:6971|220,0:7155|231,0:7849|271,0:6468"/><wd nm="teral" rd="232,0:1993|234,0:1737|235,0:1147,2742,3079"/><wd nm="teral1" rd="153,0:1727,2011"/><wd nm="terals" rd="12,0:2270|235,0:1232"/><wd nm="terate" rd="79,0:4708|256,0:4284"/><wd nm="terated" rd="194,0:2070"/><wd nm="terating" rd="142,0:700"/><wd nm="terbgalpha" rd="231,0:12369"/><wd nm="terbgcolor" rd="231,0:12321"/><wd nm="terborderalpha" rd="231,0:12589"/><wd nm="terbordercolor" rd="231,0:12538"/><wd nm="terborderthickness" rd="231,0:12474"/><wd nm="tercloning" rd="187,0:28419"/><wd nm="terclose" rd="202,0:24904,26897,27090"/><wd nm="tercontainerid" rd="131,0:675|132,0:651"/><wd nm="terday&apos;s" rd="87,0:240"/><wd nm="tered" rd="5,0:1656|8,0:1690|12,0:1905|59,0:217|133,0:1356,1820,2621,4958,5475,6373|158,0:297|159,0:375|190,0:3114"/><wd nm="terested" rd="157,0:1336,1819|158,0:474,1019,1314|160,0:2104|162,0:637,941|197,0:450|243,0:1689"/><wd nm="teresting" rd="97,0:1950"/><wd nm="terexception" rd="97,0:8692|191,0:3344,4032"/><wd nm="terface" rd="79,0:6454|97,0:2947|117,0:1427|124,0:1376|128,0:5483,6743|131,0:248|146,0:3217|147,0:2208|200,0:2256"/><wd nm="terfaces" rd="182,0:1042"/><wd nm="terhtml" rd="133,0:7504"/><wd nm="terid" rd="223,0:4575|225,0:632,643,934,951"/><wd nm="terier" rd="126,0:3479|138,0:3848"/><wd nm="terindex" rd="223,0:4017,4443|225,0:481,495,774,794"/><wd nm="tering" rd="0,0:4313|12,0:880|74,0:1809|119,0:5060|157,0:3159|161,0:310|242,0:2421"/><wd nm="teriors" rd="169,0:1215,2683|171,0:6617,7982"/><wd nm="terizer" rd="124,0:1996|126,0:2900,3257,3359,3590|138,0:519,2972,3032,3416,3626,3728,3959|145,0:1729|182,0:2419"/><wd nm="terly" rd="104,0:631,1085,1144,1203,1262,1295,1333,1522,1560,1749,1787,1976,2014,2375,2434,2493,2552,3291,3329,3879,4009|105,0:799,5431,5625,5817,6010,6263,6474,6683,6893,7224,9881,9938,9995,10052,10080,10102,10305,10327,10528,10550,10752,10774,11081,11140,11199,11258,11291,11329,11520,11558,11747,11785,11975,12013|106,0:628,1053,1110,1167,1224,1252,1274,1475,1497,1698,1720,1921,1943,2419,2476,2533,2590,3331,3353,3778,3901|107,0:2553|150,0:682,2687,2744,2801,2858,2886,2908,3082,3104,3276,3298,3471,3493,3742,3802,3862,3922,3957,3998,4166,4207,4373,4414,4581,4622|202,0:681,5559,5751,5941,6132,6384,6584,6781,6979,7304,10087,10144,10201,10258,10286,10308,10514,10536,10740,10762,10967,10989,11299,11357,11415,11473,11506,11544,11735,11773,11962,12000,12190,12228"/><wd nm="terly2005" rd="107,0:2513"/><wd nm="term" rd="143,0:327"/><wd nm="termarked" rd="188,0:324"/><wd nm="termarks" rd="188,0:1375"/><wd nm="termed" rd="19,0:312|48,0:263|62,0:421|107,0:501|213,0:605|222,0:315|263,0:906"/><wd nm="termine" rd="131,0:190,2451"/><wd nm="termined" rd="26,0:772|27,0:1413|37,0:7287|48,0:473,749|52,0:679|87,0:157|88,0:4989,44595|89,0:4438,41166|90,0:4931,9186,42303,45398,45892|91,0:4910,9165,46018,49113,49607|92,0:5141,44882|93,0:4480,41433|177,0:32830|218,0:788|227,0:841|228,0:1429|242,0:6994|247,0:17527|251,0:19353"/><wd nm="termines" rd="12,0:2566|31,0:15706|54,0:10410|57,0:6859|60,0:7369|68,0:11985|88,0:14953,37487,42005|89,0:14968,36060,39112|90,0:15406,37510,42778|91,0:16519,20148,41052,46493|92,0:15293,37772,42290|93,0:15290,36326,39378|131,0:3086|162,0:6157,19995|184,0:1626|215,0:13174|220,0:13387|231,0:14629|241,0:6076,19594|247,0:5843,17146|251,0:7004,18972|255,0:11873|271,0:12192"/><wd nm="termining" rd="172,0:322"/><wd nm="terminologies" rd="125,0:3085|128,0:29,44,89"/><wd nm="terms" rd="7,0:949,2992|49,0:761|128,0:953|141,0:241,1538|214,0:1225"/><wd nm="tern" rd="0,0:5731|31,0:20941|32,0:909,967,1688,1962,4798,4827,5446,5724|33,0:6928,7028,7155,7271,7616,7713,7838,7952,8586,8682,8805,8917,9276,9369,9490,9600,15024,15114,15231,15337,16246,16331,16444,16546|34,0:1070,1128,1175,2082,2294,5073,5102,5765,5864,5992,6109,6532,6617,6730,6832|37,0:2008,2104,2227,2339,3607,3700,3821,3931|41,0:5345,5374|42,0:5358,5387|45,0:1544,1695,1845,2915,3044,3172|46,0:11694,11723|54,0:15725|57,0:13849|60,0:14314|68,0:17300|88,0:24230|89,0:23243|90,0:24160|91,0:27593|92,0:24513|93,0:23509|138,0:8240,8281,8319|162,0:12687|177,0:10708|187,0:37868|215,0:18465|220,0:18622|231,0:19920|241,0:12282|247,0:11798|251,0:14595|255,0:7186|256,0:2435|271,0:17438"/><wd nm="ternal" rd="31,0:21564,22159,26853|37,0:227,434,776|54,0:16348,16944|60,0:14937,15533|68,0:17923,18520|88,0:24853,25449|89,0:1553,1604,2372,2425,23866,24462|90,0:24783,25379|91,0:28216,28812|92,0:25136,25732|93,0:1595,1646,2414,2467,24132,24728|94,0:9302|97,0:313,3261|113,0:2745|126,0:1400|127,0:4623,4653|129,0:1847|132,0:2578|133,0:285|143,0:150|148,0:2089,3167|154,0:6164|162,0:13310,13907,17507|163,0:2196|171,0:1537|172,0:1462,2342|177,0:13317,13912,19436,22236,32463|179,0:626|180,0:1321|196,0:1242|200,0:2570|208,0:6263|215,0:19088,19683|220,0:19245,19840|231,0:20543,21138,25496|241,0:12905,13501,17106|247,0:12421,13017|251,0:15218,15814|255,0:7809,8405|271,0:18061,18658"/><wd nm="ternalinterface" rd="97,0:2947|200,0:2256"/><wd nm="ternally" rd="24,0:3588|31,0:22052|51,0:3168|54,0:16837|58,0:3422|60,0:15426|65,0:2750|68,0:18413|80,0:5895|88,0:25342|89,0:24355|90,0:25272|91,0:28705|92,0:25625|93,0:24621|101,0:1255|102,0:2826|103,0:6475|107,0:2645|108,0:4201|109,0:4137|127,0:2240,4894,5609|129,0:3047|146,0:9274|155,0:315|160,0:3577|162,0:13800|168,0:7087|177,0:13805|187,0:20164,28092|191,0:2651,13895|195,0:666|204,0:961|206,0:7601|210,0:846|215,0:19576|217,0:3276|220,0:19733|226,0:3660|231,0:21031|240,0:3694|241,0:13394|247,0:12910|248,0:4034|251,0:15707|255,0:8298|268,0:2727|271,0:18551"/><wd nm="ternate" rd="74,0:1841|88,0:4269,26427,26610,27322,27399,27486,28088,28160,28235|89,0:3869,25440,25623,26335,26412,26499|90,0:4211,26357,26540,27253,27330,27417,28019,28091,28166|91,0:4190,29790,29973,30685,30762,30849,31451,31523,31598|92,0:4421,26709,26892,27604,27681,27768,28370,28442,28517|93,0:3911,25706,25889,26601,26678,26765|131,0:3103,3259|146,0:10490|242,0:2453|247,0:9691|249,0:804|251,0:12488|255,0:5079"/><wd nm="ternatebandcolor" rd="131,0:3195"/><wd nm="ternatebandcolors" rd="131,0:3303"/><wd nm="ternatecolorbands" rd="131,0:3048"/><wd nm="ternatehgridalpha" rd="88,0:27428|89,0:1084,1842,26441|90,0:27359|91,0:30791|92,0:27710|93,0:1126,1884,26707"/><wd nm="ternatehgridcolor" rd="88,0:1341,2205,27272,27359|89,0:1223,1248,1995,2022,26285,26372|90,0:1341,2179,27203,27290|91,0:30635,30722|92,0:1398,2322,27554,27641|93,0:1265,1290,2037,2064,26551,26638"/><wd nm="ternatevgridalpha" rd="88,0:28194|90,0:28125|91,0:31557|92,0:28476"/><wd nm="ternatevgridcolor" rd="88,0:28038,28123|90,0:27969,28054|91,0:31401,31486|92,0:28320,28405"/><wd nm="ternative" rd="133,0:2756"/><wd nm="ternet" rd="3,0:529,764|97,0:2226|103,0:6372|108,0:1672,1819,2034,2181,2305|124,0:1733|126,0:1468|146,0:2454|147,0:1234|148,0:2593,2919|190,0:767|203,0:1028"/><wd nm="terns" rd="28,0:1728|31,0:3392,3486|54,0:2059,2153|57,0:2832,2926|60,0:2819,2913|68,0:2046,2140|88,0:6148,6242|89,0:5597,5691|90,0:6090,6184|91,0:6069,6163|92,0:6300,6394|93,0:5639,5733|162,0:2469,2563|215,0:2629,2723|220,0:2817,2911|231,0:3311,3405|241,0:2598,2692|247,0:2595,2689|251,0:3862,3956|255,0:2260,2354|271,0:2035,2129"/><wd nm="terontop" rd="221,0:2888,2914|231,0:5788"/><wd nm="terparts" rd="184,0:3081,3523|187,0:4189,5327"/><wd nm="terpret" rd="22,0:1425|63,0:494|165,0:477,1450,3112|167,0:1104,2672,3841,5112,9345,9710|168,0:2496,5680|170,0:1744,3348|173,0:1074,2712|174,0:2579,4206|176,0:1183,2588,4693,6116|177,0:1150,2319|214,0:917|224,0:1303|245,0:378|247,0:9720|249,0:439|251,0:12517|253,0:422|255,0:5108"/><wd nm="terpretation" rd="87,0:116|88,0:4175,4948,44554|89,0:4397,41125|90,0:4117,4890,45851|91,0:4096,4869,49566|92,0:4327,5100,44841|93,0:4439,41392|177,0:32789|235,0:1104|247,0:17486|251,0:19312|266,0:534"/><wd nm="terpreted" rd="6,0:1596"/><wd nm="terpreting" rd="88,0:4048,26588|89,0:3782,25601|90,0:3990,26518|91,0:3969,29951|92,0:4200,26870|93,0:3824,25867"/><wd nm="terprise" rd="139,0:3465,3476|182,0:2999,3010|185,0:1856,3314"/><wd nm="terrace" rd="169,0:1127,2610|171,0:6529,7909"/><wd nm="terradius" rd="16,0:1164,4372,4441|17,0:2546,3185|18,0:3708,3762,3905,3960|31,0:12158|33,0:14665,15876|37,0:1636,3249|40,0:1244,2294|231,0:12273"/><wd nm="ters" rd="5,0:6613|6,0:1325|8,0:1115,1161,1437,2876,2922,3234|9,0:131,234,495,565,596,1341|11,0:92,1348,1396,1558,2117,2428,3205|13,0:605|14,0:1572,1633|15,0:512|16,0:392|27,0:545,1020,1246,2178,2805,5534|28,0:1949|31,0:1430,1492,4227,10152,15317|33,0:10705|37,0:12110|45,0:853|46,0:1374|53,0:1274,1901,4367|54,0:1093,1155,2891,6028,10021|57,0:1220,1282|59,0:115,172|60,0:1207,1269|62,0:169,196,592,605,737|67,0:1278,1905,3608|68,0:816,878,2928,8479,11596|69,0:520,2255,2316|71,0:2224|72,0:3075,10346,10441|74,0:3402,4981|80,0:3602|88,0:2819,2881,9779,13023,19983,42863|89,0:2657,2719,9636,13038,19997,39970|90,0:2750,2812,10232,13476,20435,43636|91,0:2729,2791,10248,14589,23765,47351|92,0:2971,3033,10326,13363,20267,43148|93,0:2699,2761,10074,13360,20263,40236|94,0:4976,5012,7197,7326,7639,8382,8460,8625|95,0:2247,2368,2553|97,0:2724,2795,3339,3423,3507,6114,6242,6367|98,0:467|100,0:1418,1480|101,0:1368|102,0:2939|103,0:1852,2222,2271,2457,6588|105,0:7943,13742|107,0:680,2020,2758|108,0:4314|109,0:1660,1677,4250|110,0:1587,1895|111,0:2186,2493|112,0:979,1320|113,128:58,87,167,275,550,1095,4562|115,0:197|116,0:747,1088|117,0:1535,1573,8179|119,0:213,2785,9018|120,0:2422|121,0:810|123,0:3577|125,0:1639,1668,1810,2930|127,0:1236,2304,2373,2405,3746,3990,4688,4757,4789,4944,4992,5061,5093|128,0:3803,9043,9089|133,0:1119,3638,3890,3984,4676,4730,5224,5734,6214,6529,6714,6864,6988|134,0:798|135,0:284,323,546,1044,1291|138,0:12623,12955|140,0:807,851|143,0:1630,2354,2525,2569,2671|144,0:1817,2585|146,0:8254,11104|150,0:5043,6053|152,0:4469,4572|154,0:9050,9127|156,0:1142,1341|159,0:598|162,0:1242,1304,20514|163,0:841,865|167,0:7044|168,0:3977|177,0:3079,3141|182,0:325|184,0:1149|185,0:2123|187,0:16300,21082,25206,25246,31457,31721,34108,42051|190,0:5316,9003|191,0:485,701,744,1517,11293|192,0:2013,2108,2144,2369,2424,3043,3079,3122,3171,3218,3294,3475,4856,6243,6325,6363,6396,7731,7760,7810,8468,8515,8592,9606,10120,13021,13304,14936,15529,16712,16758,18494,18524,22590|195,0:4953|196,0:3551,3900,11345,12008|198,0:2033,2112,2366,2440,2665,2805,2875,2913,2937,2965,3008,3200,3267,3321,3386,3427,3599,3673,4377,4448,4688,4745,4795,4828,4911|200,0:2033,2104,2648,2732,2816,5425,5553,5678|201,0:1254,2627,2652,2939,2979,5060,5100,5703|204,0:2807|205,0:6495,7262,8515,8555|206,0:307,4677,8443,8546,11140|207,0:1861|209,0:2265,2529,4916|210,0:9590|215,0:1261,1323,3511,9063,12785|218,0:238|219,0:1271,1898,4364|220,0:1449,1511,3649,9274,12998|221,0:225,1177,1981,2004,2058,2096,2206,2216,2352|222,0:1498,1523,1837,3714,3731,3776,3801,3811,3997,4033,4081|223,0:424,1590,1615,2109|224,0:132,1181|225,0:3402,3438|226,0:2264,3212,3251,3364,3414,3450|227,0:191|228,0:497,549,1024,1050,1246,1256,1658,2207,2834,3900,3994,4529,5032,5113,5572|231,0:808,835,1150,1386,1448,1613,4143,10056,14240|232,0:874,1136,1387,1530,1744|235,0:2183,2269,2558,3492|236,0:2661,2756,2997|241,0:1369,1431,20121|242,0:226,4014,5593,5894,5969,6069,6544,6606,6827,7848|243,0:1461,4300|247,0:1315,1377|251,0:2325,2387|255,0:1115,1177|256,128:18,48,898,1493,1697,4430,10325|257,0:1650,2491|258,0:209|259,128:13,38,1194,2467,3734,4178,4301,4964|261,0:2904,4171,4719,8434|270,0:1282,1909,3585|271,0:802,864,2867,8450,11803"/></pk>